{
    "height": 0.0,

    "-----------------------":0,
    "pitchApt": 0.0,
    "pitchFrq": 1,

    "kpRPY------------------":0,
    "kpTorsoR": 10.0,
    "kpTorsoP": 600.0,
    "kpTorsoY": 20.0,
    "kpUpTorsoR": 1000.0,
    "kpUpTorsoP": 1000.0,
    "kpUpTorsoY": 1000.0,

    "kpXyz-------------------":0,
    "kpTorsoX": 1000.0,
    "kpTorsoYY": 1000.0,
    "kpTorsoZ": 1000.0,
    "kpUpTorsoX": 1000.0,
    "kpUpTorsoYY": 1000.0,
    "kpUpTorsoZ": 1000.0,

    "kdRPY--------------------":0,
    "kdTorsoR": 10.0,
    "kdTorsoP": 10.0,
    "kdTorsoY": 12.0,
    "kdUpTorsoR": 60,
    "kdUpTorsoP": 10,
    "kdUpTorsoY": 80,

    "kdXyz---------------------":0,
    "kdTorsoX": 30.0,
    "kdTorsoYY": 30.0,
    "kdTorsoZ": 30.0,
    "kdUpTorsoX": 60,
    "kdUpTorsoYY": 60,
    "kdUpTorsoZ": 60,

    "FootPD RPY---------------------":0,
    "kpFootR": 2000.0,
    "kpFootP": 2000.0,
    "kpFootY": 2000.0,
    "kdFootR": 100.0,
    "kdFootP": 100.0,
    "kdFootY": 100.0,

    "FootPD XYZ---------------------":0,
    "kpFootX": 2000.0,
    "kpFootYY": 2000.0,
    "kpFootZ": 2000.0,
    "kdFootX": 100.0,
    "kdFootYY": 100.0,
    "kdFootZ": 100.0,

    "ArmPD RPY---------------------":0,
    "kpArmR": 10000.0,
    "kpArmP": 10000.0,
    "kpArmY": 10000.0,
    "kdArmR": 100.0,
    "kdArmP": 100.0,
    "kdArmY": 100.0,

    "ArmPD XYZ---------------------":0,
    "kpArmX": 10000.0,
    "kpArmYY": 10000.0,
    "kpArmZ": 10000.0,
    "kdArmX": 100.0,
    "kdArmYY": 100.0,
    "kdArmZ": 100.0,

    "weight GVL------------------":0,
    "weightGVL": 100,
    "weightGVL10": 8000000,
    "weightGVLKnee": 100,
    "weightGVLAnkle": 100,

    "FBD-------------------------":0,
    "weightFBD": 10,

    "wei Foot Force--------------":0,
    "weightFootForceR": 100,
    "weightFootForceP": 100,
    "weightFootForceYaw": 1000,
    "weightFootForceX": 30,
    "weightFootForceY": 30,
    "weightFootForceZ": 1250,

    "wei Arm Force----------------":0,
    "weightArmForceR": 1800000,
    "weightArmForceP": 1800000,
    "weightArmForceYaw": 18000000,
    "weightArmForceX": 1800000,
    "weightArmForceY": 1800000,
    "weightArmForceZ": 1820000,

    "wei EE Pos-------------------":0,
    "weightFootPos": 120000,
    "weightArmPos": 600,
    "weightFootYaw": 200000,
    "weightArmRPY": 600,
    "weightArmZ": 800,

    "weightTorso-------------------":0,
    "weightTorsoPos":600000,
    "weightTorsoRPY":600000,

    "hqp wei Foot Force--------------":0,
    "hweightFootForceR": 10,
    "hweightFootForceP": 10,
    "hweightFootForceYaw": 50,
    "hweightFootForceX": 10,
    "hweightFootForceY": 10,
    "hweightFootForceZ": 50,

    "hqp wei Arm Force----------------":0,
    "hweightArmForceR": 10,
    "hweightArmForceP": 10,
    "hweightArmForceYaw": 10,
    "hweightArmForceX": 30,
    "hweightArmForceY": 30,
    "hweightArmForceZ": 30,

    "hqp wei Foot Pose-------------------":0,
    "hweightFootPoseR": 1,
    "hweightFootPoseP": 1,
    "hweightFootPoseYaw": 1,
    "hweightFootPoseX": 1,
    "hweightFootPoseY": 1,
    "hweightFootPoseZ": 1,

    "hqp wei Arm Pose----------------":0,
    "hweightArmPoseR": 1,
    "hweightArmPoseP": 1,
    "hweightArmPoseYaw": 1,
    "hweightArmPoseX": 1,
    "hweightArmPoseY": 1,
    "hweightArmPoseZ": 1,

    "hqp weightTorso-------------------":0,
    "hweightTorsoPos":1,
    "hweightTorsoRPY":1,

    "hqp task's hierarchy--------------":0,
    "GVL":7,
    "UpTorsoRPY":4,
    "UpTorsoXYZ":5,
    "ForceFoot":5,
    "ForceArm":4,
    "ComRPY":3,
    "ComXYZ":2,
    
    "PoseArm":4,
    "TorsoRPY":3,
    "TorsoXYZ":2,
    "PoseFoot":1,
    "Dynamic":0,

    "damp------------------------":0,
    "damp":0.001
}